{
  "annotations": {
    "list": [
      {
        "builtIn": 1,
        "datasource": {
          "type": "grafana",
          "uid": "-- Grafana --"
        },
        "enable": true,
        "hide": true,
        "iconColor": "rgba(0, 211, 255, 1)",
        "name": "Annotations & Alerts",
        "type": "dashboard"
      }
    ]
  },
  "editable": true,
  "graphTooltip": 0,
  "links": [],
  "panels": [
    {
      "datasource": {
        "type": "prometheus",
        "uid": "Prometheus"
      },
      "fieldConfig": {
        "defaults": {
          "mappings": [
            {
              "options": {
                "0": {
                  "text": "ALERT"
                },
                "1": {
                  "text": "OK"
                }
              },
              "type": "value"
            }
          ],
          "thresholds": {
            "mode": "absolute",
            "steps": [
              {
                "color": "red",
                "value": null
              },
              {
                "color": "green",
                "value": 1
              }
            ]
          }
        },
        "overrides": []
      },
      "gridPos": {
        "h": 4,
        "w": 4,
        "x": 0,
        "y": 0
      },
      "id": 1,
      "options": {
        "colorMode": "background",
        "graphMode": "none",
        "justifyMode": "center",
        "orientation": "auto",
        "reduceOptions": {
          "calcs": [
            "lastNotNull"
          ],
          "fields": "",
          "values": false
        },
        "textMode": "auto",
        "wideLayout": true
      },
      "targets": [
        {
          "expr": "kaspa_watchtower_status_ok{node=\"$node\"}",
          "legendFormat": "status",
          "refId": "A"
        }
      ],
      "title": "Status",
      "type": "stat"
    },
    {
      "datasource": {
        "type": "prometheus",
        "uid": "Prometheus"
      },
      "fieldConfig": {
        "defaults": {
          "mappings": [
            {
              "options": {
                "0": {
                  "text": "OK"
                },
                "1": {
                  "text": "WARN"
                },
                "2": {
                  "text": "CRITICAL"
                }
              },
              "type": "value"
            }
          ],
          "thresholds": {
            "mode": "absolute",
            "steps": [
              {
                "color": "green",
                "value": null
              },
              {
                "color": "orange",
                "value": 1
              },
              {
                "color": "red",
                "value": 2
              }
            ]
          }
        },
        "overrides": []
      },
      "gridPos": {
        "h": 4,
        "w": 4,
        "x": 4,
        "y": 0
      },
      "id": 2,
      "options": {
        "colorMode": "background",
        "graphMode": "none",
        "justifyMode": "center",
        "orientation": "auto",
        "reduceOptions": {
          "calcs": [
            "lastNotNull"
          ],
          "fields": "",
          "values": false
        },
        "textMode": "auto",
        "wideLayout": true
      },
      "targets": [
        {
          "expr": "kaspa_watchtower_severity_value{node=\"$node\"}",
          "legendFormat": "severity",
          "refId": "A"
        }
      ],
      "title": "Severity",
      "type": "stat"
    },
    {
      "datasource": {
        "type": "prometheus",
        "uid": "Prometheus"
      },
      "fieldConfig": {
        "defaults": {
          "thresholds": {
            "mode": "absolute",
            "steps": [
              {
                "color": "red",
                "value": null
              },
              {
                "color": "green",
                "value": 1
              }
            ]
          }
        },
        "overrides": []
      },
      "gridPos": {
        "h": 4,
        "w": 4,
        "x": 8,
        "y": 0
      },
      "id": 3,
      "options": {
        "colorMode": "value",
        "graphMode": "none",
        "justifyMode": "center",
        "orientation": "auto",
        "reduceOptions": {
          "calcs": [
            "lastNotNull"
          ],
          "fields": "",
          "values": false
        },
        "textMode": "auto",
        "wideLayout": true
      },
      "targets": [
        {
          "expr": "kaspa_watchtower_peer_count{node=\"$node\"}",
          "legendFormat": "peers",
          "refId": "A"
        }
      ],
      "title": "Peers",
      "type": "stat"
    },
    {
      "datasource": {
        "type": "prometheus",
        "uid": "Prometheus"
      },
      "fieldConfig": {
        "defaults": {
          "thresholds": {
            "mode": "absolute",
            "steps": [
              {
                "color": "red",
                "value": null
              },
              {
                "color": "green",
                "value": 1
              }
            ]
          }
        },
        "overrides": []
      },
      "gridPos": {
        "h": 4,
        "w": 4,
        "x": 12,
        "y": 0
      },
      "id": 4,
      "options": {
        "colorMode": "value",
        "graphMode": "none",
        "justifyMode": "center",
        "orientation": "auto",
        "reduceOptions": {
          "calcs": [
            "lastNotNull"
          ],
          "fields": "",
          "values": false
        },
        "textMode": "auto",
        "wideLayout": true
      },
      "targets": [
        {
          "expr": "kaspa_watchtower_synced{node=\"$node\"}",
          "legendFormat": "synced",
          "refId": "A"
        }
      ],
      "title": "Synced",
      "type": "stat"
    },
    {
      "datasource": {
        "type": "prometheus",
        "uid": "Prometheus"
      },
      "fieldConfig": {
        "defaults": {
          "unit": "short"
        },
        "overrides": []
      },
      "gridPos": {
        "h": 8,
        "w": 12,
        "x": 0,
        "y": 4
      },
      "id": 5,
      "options": {
        "legend": {
          "calcs": [
            "lastNotNull"
          ],
          "displayMode": "list",
          "placement": "bottom",
          "showLegend": true
        },
        "tooltip": {
          "mode": "single",
          "sort": "none"
        }
      },
      "targets": [
        {
          "expr": "kaspa_watchtower_virtual_daa_score{node=\"$node\"}",
          "legendFormat": "DAA",
          "refId": "A"
        },
        {
          "expr": "kaspa_watchtower_block_count{node=\"$node\"}",
          "legendFormat": "blocks",
          "refId": "B"
        }
      ],
      "title": "DAG Progress",
      "type": "timeseries"
    },
    {
      "datasource": {
        "type": "prometheus",
        "uid": "Prometheus"
      },
      "fieldConfig": {
        "defaults": {
          "unit": "short"
        },
        "overrides": []
      },
      "gridPos": {
        "h": 8,
        "w": 12,
        "x": 12,
        "y": 4
      },
      "id": 6,
      "options": {
        "legend": {
          "calcs": [
            "lastNotNull"
          ],
          "displayMode": "list",
          "placement": "bottom",
          "showLegend": true
        },
        "tooltip": {
          "mode": "single",
          "sort": "none"
        }
      },
      "targets": [
        {
          "expr": "kaspa_watchtower_relay_blocks_window{node=\"$node\"}",
          "legendFormat": "relay blocks",
          "refId": "A"
        },
        {
          "expr": "kaspa_watchtower_relay_events_window{node=\"$node\"}",
          "legendFormat": "relay events",
          "refId": "B"
        }
      ],
      "title": "Relay Progress Window",
      "type": "timeseries"
    },
    {
      "datasource": {
        "type": "prometheus",
        "uid": "Prometheus"
      },
      "fieldConfig": {
        "defaults": {
          "unit": "short"
        },
        "overrides": []
      },
      "gridPos": {
        "h": 7,
        "w": 8,
        "x": 0,
        "y": 12
      },
      "id": 7,
      "options": {
        "legend": {
          "calcs": [
            "lastNotNull"
          ],
          "displayMode": "list",
          "placement": "bottom",
          "showLegend": true
        },
        "tooltip": {
          "mode": "single",
          "sort": "none"
        }
      },
      "targets": [
        {
          "expr": "kaspa_watchtower_benchmark_daa_rate_per_hour{node=\"$node\"}",
          "legendFormat": "DAA / h",
          "refId": "A"
        },
        {
          "expr": "kaspa_watchtower_benchmark_block_rate_per_hour{node=\"$node\"}",
          "legendFormat": "blocks / h",
          "refId": "B"
        }
      ],
      "title": "Benchmark Rates",
      "type": "timeseries"
    },
    {
      "datasource": {
        "type": "prometheus",
        "uid": "Prometheus"
      },
      "fieldConfig": {
        "defaults": {
          "unit": "decgbytes"
        },
        "overrides": []
      },
      "gridPos": {
        "h": 7,
        "w": 8,
        "x": 8,
        "y": 12
      },
      "id": 8,
      "options": {
        "legend": {
          "calcs": [
            "lastNotNull"
          ],
          "displayMode": "list",
          "placement": "bottom",
          "showLegend": true
        },
        "tooltip": {
          "mode": "single",
          "sort": "none"
        }
      },
      "targets": [
        {
          "expr": "kaspa_watchtower_disk_free_gb{node=\"$node\"}",
          "legendFormat": "free GiB",
          "refId": "A"
        },
        {
          "expr": "kaspa_watchtower_benchmark_disk_free_delta_gb{node=\"$node\"}",
          "legendFormat": "benchmark delta GiB",
          "refId": "B"
        }
      ],
      "title": "Disk",
      "type": "timeseries"
    },
    {
      "datasource": {
        "type": "prometheus",
        "uid": "Prometheus"
      },
      "fieldConfig": {
        "defaults": {
          "custom": {
            "align": "auto",
            "cellOptions": {
              "type": "auto"
            },
            "inspect": false
          }
        },
        "overrides": []
      },
      "gridPos": {
        "h": 7,
        "w": 8,
        "x": 16,
        "y": 12
      },
      "id": 9,
      "options": {
        "cellHeight": "sm",
        "footer": {
          "countRows": false,
          "fields": "",
          "reducer": [
            "sum"
          ],
          "show": false
        },
        "showHeader": true
      },
      "targets": [
        {
          "expr": "kaspa_watchtower_check_ok{node=\"$node\"}",
          "format": "table",
          "instant": true,
          "legendFormat": "{{check}}",
          "refId": "A"
        }
      ],
      "title": "Checks",
      "type": "table"
    },
    {
      "datasource": {
        "type": "prometheus",
        "uid": "Prometheus"
      },
      "fieldConfig": {
        "defaults": {
          "decimals": 0
        },
        "overrides": []
      },
      "gridPos": {
        "h": 5,
        "w": 8,
        "x": 0,
        "y": 19
      },
      "id": 10,
      "options": {
        "colorMode": "value",
        "graphMode": "none",
        "justifyMode": "center",
        "orientation": "auto",
        "reduceOptions": {
          "calcs": [
            "lastNotNull"
          ],
          "fields": "",
          "values": false
        },
        "textMode": "auto",
        "wideLayout": true
      },
      "targets": [
        {
          "expr": "kaspa_watchtower_recovery_attempts_total{node=\"$node\"}",
          "legendFormat": "attempts",
          "refId": "A"
        },
        {
          "expr": "kaspa_watchtower_recovery_executed_total{node=\"$node\"}",
          "legendFormat": "executed",
          "refId": "B"
        },
        {
          "expr": "kaspa_watchtower_recovery_dry_runs_total{node=\"$node\"}",
          "legendFormat": "dry-runs",
          "refId": "C"
        },
        {
          "expr": "kaspa_watchtower_recovery_skipped_total{node=\"$node\"}",
          "legendFormat": "skipped",
          "refId": "D"
        }
      ],
      "title": "Recovery Counts",
      "type": "stat"
    },
    {
      "datasource": {
        "type": "prometheus",
        "uid": "Prometheus"
      },
      "fieldConfig": {
        "defaults": {
          "unit": "dateTimeAsIso"
        },
        "overrides": []
      },
      "gridPos": {
        "h": 5,
        "w": 8,
        "x": 8,
        "y": 19
      },
      "id": 11,
      "options": {
        "colorMode": "value",
        "graphMode": "none",
        "justifyMode": "center",
        "orientation": "auto",
        "reduceOptions": {
          "calcs": [
            "lastNotNull"
          ],
          "fields": "",
          "values": false
        },
        "textMode": "auto",
        "wideLayout": true
      },
      "targets": [
        {
          "expr": "kaspa_watchtower_recovery_last_started_timestamp_seconds{node=\"$node\"} * 1000",
          "legendFormat": "last started",
          "refId": "A"
        },
        {
          "expr": "kaspa_watchtower_recovery_last_completed_timestamp_seconds{node=\"$node\"} * 1000",
          "legendFormat": "last completed",
          "refId": "B"
        }
      ],
      "title": "Last Recovery",
      "type": "stat"
    },
    {
      "datasource": {
        "type": "prometheus",
        "uid": "Prometheus"
      },
      "fieldConfig": {
        "defaults": {
          "decimals": 0
        },
        "overrides": []
      },
      "gridPos": {
        "h": 5,
        "w": 8,
        "x": 16,
        "y": 19
      },
      "id": 12,
      "options": {
        "legend": {
          "calcs": [
            "lastNotNull"
          ],
          "displayMode": "list",
          "placement": "bottom",
          "showLegend": true
        },
        "tooltip": {
          "mode": "single",
          "sort": "none"
        }
      },
      "targets": [
        {
          "expr": "kaspa_watchtower_recovery_attempts_total{node=\"$node\"}",
          "legendFormat": "attempts",
          "refId": "A"
        },
        {
          "expr": "kaspa_watchtower_recovery_executed_total{node=\"$node\"}",
          "legendFormat": "executed",
          "refId": "B"
        },
        {
          "expr": "kaspa_watchtower_recovery_skipped_total{node=\"$node\"}",
          "legendFormat": "skipped",
          "refId": "C"
        }
      ],
      "title": "Recovery Trend",
      "type": "timeseries"
    }
  ],
  "refresh": "30s",
  "schemaVersion": 39,
  "tags": [
    "kaspa",
    "watchtower",
    "openclaw"
  ],
  "templating": {
    "list": [
      {
        "current": {
          "selected": false,
          "text": "kaspa-tn10-local",
          "value": "kaspa-tn10-local"
        },
        "datasource": {
          "type": "prometheus",
          "uid": "Prometheus"
        },
        "definition": "label_values(kaspa_watchtower_status_ok, node)",
        "hide": 0,
        "includeAll": false,
        "label": "Node",
        "multi": false,
        "name": "node",
        "options": [],
        "query": {
          "query": "label_values(kaspa_watchtower_status_ok, node)",
          "refId": "StandardVariableQuery"
        },
        "refresh": 1,
        "regex": "",
        "skipUrlSync": false,
        "sort": 1,
        "type": "query"
      }
    ]
  },
  "time": {
    "from": "now-6h",
    "to": "now"
  },
  "timepicker": {},
  "timezone": "browser",
  "title": "Kaspa Watchtower",
  "uid": "kaspa-watchtower",
  "version": 2,
  "weekStart": ""
}
